gaana
