Metadata-Version: 1.1
Name: gaana
Version: 0.0.2
Summary: Download songs from gaana.com from command line `gaana`
Home-page: https://github.com/zonito/gaana
Author: Love Sharma
Author-email: contact@lovesharma.com
License: UNKNOWN
Download-URL: https://github.com/zonito/gaana/archive/0.0.2.tar.gz
Keywords: download,gaana,gana,song,songs
Platform: UNKNOWN
